gitsecrets/__init__.py
tests/__init__.py
python_git_secrets-0.1.3.dist-info/LICENSE
python_git_secrets-0.1.3.dist-info/METADATA
python_git_secrets-0.1.3.dist-info/WHEEL
python_git_secrets-0.1.3.dist-info/top_level.txt
python_git_secrets-0.1.3.dist-info/RECORD
