Metadata-Version: 2.1
Name: python-git-secrets
Version: 0.1.3
Summary: Python implementation of git-secrets
Home-page: https://github.com/mbacchi/python-git-secrets
Author: Matt Bacchi
Author-email: mbacchi@gmail.com
License: BSD (Simplified)
Platform: Posix; MacOS X; Windows
Classifier: Development Status :: 3 - Alpha
Classifier: Intended Audience :: System Administrators
Classifier: License :: OSI Approved :: BSD License
Classifier: Operating System :: OS Independent
Classifier: Programming Language :: Python :: 3
Classifier: Programming Language :: Python :: 3.5
Classifier: Programming Language :: Python :: 3.6
Classifier: Programming Language :: Python :: 3.7
Classifier: Programming Language :: Python :: 3.8
Classifier: Topic :: System :: Systems Administration
Requires-Python: >=3
Requires-Dist: dulwich
